dashtable/ext/__init__.py
dashtable/ext/presetstyle.py
dashtable/ext/rst2ascii.py
dashtable_ext-1.0.0.dist-info/LICENSE
dashtable_ext-1.0.0.dist-info/METADATA
dashtable_ext-1.0.0.dist-info/WHEEL
dashtable_ext-1.0.0.dist-info/top_level.txt
dashtable_ext-1.0.0.dist-info/RECORD
