Metadata-Version: 2.1
Name: dashtable-ext
Version: 1.0.0
Summary: Extension for doakey3/DashTable
Author-email: Abdullah Al Muaz <abdullahalmuaz15@gmail.com>
License: MIT License
Project-URL: Homepage, https://github.com/aurkaxi/dashtable-ext
Keywords: table,extension,dashtable
Classifier: Development Status :: 1 - Planning
Classifier: License :: OSI Approved :: MIT License
Classifier: Intended Audience :: Developers
Classifier: Natural Language :: English
Classifier: Operating System :: OS Independent
Classifier: Programming Language :: Python :: 3.11
Requires-Python: >=3.10
License-File: LICENSE
Requires-Dist: dashtable
